szczypiorek/__init__.py
szczypiorek/cli.py
szczypiorek/constants.py
szczypiorek/crypto.py
szczypiorek/env_validators.py
szczypiorek/exceptions.py
szczypiorek/fields.py
szczypiorek/fields_validators.py
szczypiorek/git.py
szczypiorek/parser.py
szczypiorek/utils.py
szczypiorek-1.1.3.dist-info/entry_points.txt
szczypiorek-1.1.3.dist-info/WHEEL
szczypiorek-1.1.3.dist-info/METADATA
szczypiorek-1.1.3.dist-info/RECORD
