Metadata-Version: 2.1
Name: szczypiorek
Version: 1.1.3
Summary: Szczypiorek environment management for humans.
Home-page: https://github.com/cosphere-org/szczypiorek
Keywords: szczypiorek,environment,secrets
Author: CoSphere Tech
Author-email: contact@cosphere.org
Requires-Python: >=3.9.9,<3.10.0
Classifier: Programming Language :: Python :: 3
Classifier: Topic :: Software Development :: Libraries :: Python Modules
Requires-Dist: PyYAML (>=6.0,<7.0)
Requires-Dist: bash (>=0.6,<0.7)
Requires-Dist: click (>=8.0.3,<9.0.0)
Requires-Dist: python-gnupg (>=0.4.8,<0.5.0)
Requires-Dist: validators (>=0.18.2,<0.19.0)
Project-URL: Repository, https://github.com/cosphere-org/szczypiorek
